cosmica/__init__.py
cosmica/comm_link/__init__.py
cosmica/comm_link/base.py
cosmica/comm_link/coordinator.py
cosmica/comm_link/gateway_to_gateway.py
cosmica/comm_link/gateway_to_internet.py
cosmica/comm_link/geometric.py
cosmica/comm_link/rate_distance_calculator.py
cosmica/comm_link/sat_to_ground.py
cosmica/comm_link/sat_to_sat.py
cosmica/comm_link/uncertainty.py
cosmica/dtos/__init__.py
cosmica/dtos/dynamics_data.py
cosmica/dynamics/__init__.py
cosmica/dynamics/constellation.py
cosmica/dynamics/orbit.py
cosmica/dynamics/plotting.py
cosmica/dynamics/sun_dynamics.py
cosmica/experimental_packet_routing/__init__.py
cosmica/experimental_packet_routing/calc_forwarding_table_from_graph.py
cosmica/experimental_packet_routing/case_definitions.py
cosmica/experimental_packet_routing/comm_data.py
cosmica/experimental_packet_routing/dtos.py
cosmica/experimental_packet_routing/forwarding_table.py
cosmica/experimental_packet_routing/forwarding_table_time_list.py
cosmica/experimental_packet_routing/lsa_case_definition.py
cosmica/experimental_packet_routing/node_knowledge.py
cosmica/experimental_packet_routing/routing_result_visualizer.py
cosmica/experimental_packet_routing/simulator.py
cosmica/experimental_packet_routing/space_time_graph.py
cosmica/experimental_packet_routing/use_node_knowledge.py
cosmica/experimental_packet_routing/utility.py
cosmica/models/__init__.py
cosmica/models/constellation.py
cosmica/models/demand.py
cosmica/models/gateway.py
cosmica/models/internet.py
cosmica/models/node.py
cosmica/models/orbit.py
cosmica/models/satellite.py
cosmica/models/scenario.py
cosmica/models/terminal.py
cosmica/models/user.py
cosmica/py.typed
cosmica/scenario/__init__.py
cosmica/scenario/assets/aggregated_population_data.npy
cosmica/scenario/assets/maritime_20231001_non-loitering.npy
cosmica/scenario/maritime.py
cosmica/scenario/population.py
cosmica/topology/__init__.py
cosmica/topology/gateway_to_gateway.py
cosmica/topology/gateway_to_internet.py
cosmica-0.4.0.dist-info/licenses/LICENSE-APACHE
cosmica-0.4.0.dist-info/licenses/LICENSE-MIT
cosmica-0.4.0.dist-info/WHEEL
cosmica-0.4.0.dist-info/METADATA
cosmica-0.4.0.dist-info/RECORD
